[
    {
        "field_name": "uuid",
        "constraint": "PRI",
        "type": "bigint unsigned",
        "description": "doctors unique id",
        "size": "8",
        "table": "doctors"
    },
    {
        "field_name": "name",
        "constraint": "NN",
        "type": "varchar(255)",
        "description": "doctors name",
        "size": "255",
        "table": "doctors"
    },
    {
        "field_name": "password",
        "constraint": "NN",
        "type": "char(64)",
        "description": "doctors password",
        "size": "64",
        "table": "doctors"
    },
    {
        "field_name": "email",
        "constraint": "NN",
        "type": "varchar(255)",
        "description": "doctors email",
        "size": "255",
        "table": "doctors"
    },
    {
        "field_name": "registration_date",
        "constraint": "current_timestamp()",
        "type": "datetime",
        "description": "doctors registration date",
        "size": "8",
        "table": "doctors"
    },
    {
        "field_name": "uuid",
        "constraint": "PRI",
        "type": "bigint unsigned",
        "description": "patients unique id",
        "size": "8",
        "table": "pacients"
    },
    {
        "field_name": "name",
        "constraint": "NN",
        "type": "varchar(255)",
        "description": "patients name",
        "size": "255",
        "table": "pacients"
    },
    {
        "field_name": "username",
        "constraint": "UNI",
        "type": "varchar(255)",
        "description": "patients username",
        "size": "255",
        "table": "pacients"
    },
    {
        "field_name": "password",
        "constraint": "NN",
        "type": "char(64)",
        "description": "patients password",
        "size": "64",
        "table": "pacients"
    },
    {
        "field_name": "email",
        "constraint": "NN",
        "type": "varchar(255)",
        "description": "patients email",
        "size": "255",
        "table": "pacients"
    },
    {
        "field_name": "phone",
        "constraint": "NN",
        "type": "varchar(20)",
        "description": "patients phone",
        "size": "20",
        "table": "pacients"
    },
    {
        "field_name": "tutor_email",
        "constraint": "NN",
        "type": "varchar(255)",
        "description": "email of the patient's tutor",
        "size": "255",
        "table": "pacients"
    },
    {
        "field_name": "birthday",
        "constraint": "N/A",
        "type": "date",
        "description": "patients birthday",
        "size": "8",
        "table": "pacients"
    },
    {
        "field_name": "appointments_count",
        "constraint": "0",
        "type": "int(10) unsigned",
        "description": "number of appointments this patient has",
        "size": "10",
        "table": "pacients"
    },
    {
        "field_name": "last_seen",
        "constraint": "N/A",
        "type": "datetime",
        "description": "last time this patient has logged in",
        "size": "8",
        "table": "pacients"
    },
    {
        "field_name": "created_at",
        "constraint": "current_timestamp()",
        "type": "datetime",
        "description": "date of creation",
        "size": "8",
        "table": "pacients"
    },
    {
        "field_name": "genere",
        "constraint": "M",
        "type": "enum('M','F')",
        "description": "the patient's genere",
        "size": "1",
        "table": "pacients"
    },
    {
        "field_name": "pacient_uuid",
        "constraint": "PRI",
        "type": "bigint unsigned",
        "description": "the patient's unique id",
        "size": "8",
        "table": "pacientsDoctors"
    },
    {
        "field_name": "doctor_uuid",
        "constraint": "PRI",
        "type": "bigint unsigned",
        "description": "the doctor's unique id",
        "size": "8",
        "table": "pacientsDoctors"
    },
    {
        "field_name": "questionary",
        "constraint": "PRI",
        "type": "int(10) unsigned",
        "description": "the questionary's unique id",
        "size": "10",
        "table": "questionaryMeasures"
    },
    {
        "field_name": "stat",
        "constraint": "PRI",
        "type": "int(10) unsigned",
        "description": "the stat's unique id",
        "size": "8",
        "table": "questionaryMeasures"
    },
    {
        "field_name": "id",
        "constraint": "PRI",
        "type": "int(10) unsigned",
        "description": "questionary's unique id",
        "size": "10",
        "table": "questionarys"
    },
    {
        "field_name": "path_to_file",
        "constraint": "NN",
        "type": "varchar(255)",
        "description": "path to the file where the questionary is defined",
        "size": "255",
        "table": "questionarys"
    },
    {
        "field_name": "name",
        "constraint": "NN",
        "type": "varchar(255)",
        "description": "questionary's name",
        "size": "255",
        "table": "questionarys"
    },
    {
        "field_name": "length",
        "constraint": "NN",
        "type": "int(10) unsigned",
        "description": "count of questions in the questionary",
        "size": "8",
        "table": "questionarys"
    },
    {
        "field_name": "created_at",
        "constraint": "current_timestamp()",
        "type": "datetime",
        "description": "date of creation",
        "size": "8",
        "table": "questionarys"
    },
    {
        "field_name": "short_name",
        "constraint": "UNI",
        "type": "varchar(255)",
        "description": "acronym of the questionary's name",
        "size": "255",
        "table": "questionarys"
    },
    {
        "field_name": "creator",
        "constraint": "MUL",
        "type": "bigint unsigned",
        "description": "doctor who created the questionary",
        "size": "8",
        "table": "questionarys"
    },
    {
        "field_name": "id",
        "constraint": "PRI",
        "type": "int(10) unsigned",
        "description": "questionary set id",
        "size": "8",
        "table": "questionarysSet"
    },
    {
        "field_name": "name",
        "constraint": "NN",
        "type": "varchar(255)",
        "description": "questionary set name",
        "size": "255",
        "table": "questionarysSet"
    },
    {
        "field_name": "created_at",
        "constraint": "current_timestamp()",
        "type": "datetime",
        "description": " date of creation",
        "size": "8",
        "table": "questionarysSet"
    },
    {
        "field_name": "path_to_file",
        "constraint": "NN",
        "type": "varchar(255)",
        "description": "path to the file where the questionary set is defined",
        "size": "255",
        "table": "questionarysSet"
    },
    {
        "field_name": "creator",
        "constraint": "MUL",
        "type": "bigint unsigned",
        "description": "who created the questionary set",
        "size": "8",
        "table": "questionarysSet"
    },
    {
        "field_name": "questionarySet",
        "constraint": "PRI",
        "type": "int(10) unsigned",
        "description": "questionary set id",
        "size": "8",
        "table": "questionarysSetQuestionarys"
    },
    {
        "field_name": "questionary",
        "constraint": "PRI",
        "type": "int(10) unsigned",
        "description": "questionary id",
        "size": "8",
        "table": "questionarysSetQuestionarys"
    },
    {
        "field_name": "id",
        "constraint": "PRI",
        "type": "int(10) unsigned",
        "description": "revision's unique id",
        "size": "8",
        "table": "revisions"
    },
    {
        "field_name": "created_at",
        "constraint": "current_timestamp()",
        "type": "datetime",
        "description": "the date when the revision was created",
        "size": "8",
        "table": "revisions"
    },
    {
        "field_name": "starts_at",
        "constraint": "N/A",
        "type": "datetime",
        "description": "when the revision is set to start",
        "size": "8",
        "table": "revisions"
    },
    {
        "field_name": "expires_at",
        "constraint": "N/A",
        "type": "datetime",
        "description": "when the revision is no longer accessible",
        "size": "8",
        "table": "revisions"
    },
    {
        "field_name": "was_finished",
        "constraint": "0",
        "type": "tinyint(1)",
        "description": "if the revision was finished",
        "size": "8",
        "table": "revisions"
    },
    {
        "field_name": "finished_at",
        "constraint": "N/A",
        "type": "datetime",
        "description": "when the revision was finished",
        "size": "8",
        "table": "revisions"
    },
    {
        "field_name": "was_canceled",
        "constraint": "0",
        "type": "tinyint(1)",
        "description": "if the revision was canceled",
        "size": "8",
        "table": "revisions"
    },
    {
        "field_name": "show_to_pacient",
        "constraint": "1",
        "type": "tinyint(1)",
        "description": "if the revision is visible to the pacient",
        "size": "8",
        "table": "revisions"
    },
    {
        "field_name": "questionary",
        "constraint": "MUL",
        "type": "int(10) unsigned",
        "description": "the questionary set id",
        "size": "8",
        "table": "revisions"
    },
    {
        "field_name": "pacient",
        "constraint": "MUL",
        "type": "bigint unsigned",
        "description": "th id of the pacient",
        "size": "8",
        "table": "revisions"
    },
    {
        "field_name": "creator",
        "constraint": "MUL",
        "type": "bigint unsigned",
        "description": "the doctor who created the revision",
        "size": "8",
        "table": "revisions"
    },
    {
        "field_name": "id",
        "constraint": "PRI",
        "type": "int(10) unsigned",
        "description": "the stat's unique id",
        "size": "8",
        "table": "stats"
    },
    {
        "field_name": "name",
        "constraint": "NN",
        "type": "varchar(255)",
        "description": "the stat's name",
        "size": "255",
        "table": "stats"
    }
]